cryptrade/__init__.py
cryptrade/binance.py
cryptrade/bitfinex.py
cryptrade/coinbase.py
cryptrade/exceptions.py
cryptrade/exchange_api.py
cryptrade/kraken.py
cryptrade/logging.py
cryptrade/monitor.py
cryptrade/observers.py
cryptrade/parameters.py
cryptrade-1.103.dist-info/METADATA
cryptrade-1.103.dist-info/WHEEL
cryptrade-1.103.dist-info/top_level.txt
cryptrade-1.103.dist-info/RECORD
