Metadata-Version: 2.1
Name: cryptrade
Version: 1.103
Summary: Basic crypto trading API for developing trading bots with transparent access to Coinbase Pro, Binance, Kraken, and Bitfinex
Home-page: https://github.com/elnkosc/cryptrade/
Author: Koen Schilders
Author-email: koen@schilders.org
License: GNU General Public License v3.0
Platform: UNKNOWN
